{
  "language": "en",
  "plugin": "org.kohsuke.freetrain.rail.signal2",
  "sourceManifest": "plugin.xml",
  "texts": [
    {
      "key": "plugin.title",
      "source": "鉄道用信号機",
      "translation": "Railway signal"
    },
    {
      "key": "contribution.{6FA55843-E694-4140-A121-0A3D0C613B22}-r.name",
      "source": "停車位置票",
      "translation": "Stopping Position Marker"
    },
    {
      "key": "contribution.{6FA55844-E695-4141-A122-0A3D0C613B23}-r.name",
      "source": "誘導信号機",
      "translation": "Shunting signal"
    },
    {
      "key": "contribution.{6FA55844-E695-4141-A133-0A3D0C613B23}-r.name",
      "source": "入換信号機",
      "translation": "Shunting Signal"
    }
  ]
}
